{
  "descriptions": {
    "en": [
      "Extract all students' name and age whose age is",
      "between 19 and 25."
    ],
    "jp": [
      "年齢が19歳から25歳の間の生徒の、名前と年齢を取り出してください。"
    ]
  },
  "create_sql": [
    "create table Students (",
    "       id int primary key,",
    "       name varchar(16),",
    "       age int",
    ");"
  ],
  "insert_sql": [
    "insert into Students values",
    "       (1, 'Alice', 16),",
    "       (2, 'Bob', 18),",
    "       (3, 'Charlie', 15),",
    "       (4, 'Dave', 23),",
    "       (5, 'Emilia', 29),",
    "       (6, 'François', 24),",
    "       (7, 'Günter', 16),",
    "       (8, 'Hàoyǔ', 21),",
    "       (9, 'Iori', 20)",
    ";"
  ],
  "tables": [
    {
      "name": "Students",
      "columns": ["id", "name", "age"],
      "records": [
        [1, "Alice", 16],
        [2, "Bob", 18],
        [3, "Charlie", 15],
        [4, "Dave", 23],
        [5, "Emilia", 29],
        [6, "François", 24],
        [7, "Günter", 16],
        [8, "Hàoyǔ", 21],
        [9, "Iori", 20]
      ]
    }
  ],
  "expected": {
    "expected_columns": ["name", "age"],
    "expected_types": ["varchar", "int"],
    "expected_result": [
      ["Dave", 23],
      ["François", 24],
      ["Hàoyǔ", 21],
      ["Iori", 20]
    ],
    "order_strict": false
  },
  "writers": [
    "ryhoh"
  ]
}
